basic_components/__init__.py
basic_components/component_dependencies.toml
basic_components/cli/__init__.py
basic_components/cli/components.py
basic_components/utils/__init__.py
basic_components/utils/jinjax.py
basic_components/utils/tailwind.py
basic_components-0.3.0.dist-info/METADATA
basic_components-0.3.0.dist-info/WHEEL
basic_components-0.3.0.dist-info/entry_points.txt
basic_components-0.3.0.dist-info/licenses/LICENSE
basic_components-0.3.0.dist-info/RECORD
