Metadata-Version: 2.3
Name: basic-components
Version: 0.3.0
Summary: Re-usable server-side components based on shadcn/ui with JinjaX, Alpine.js and Tailwind CSS
Project-URL: Homepage, https://github.com/basicmachines-co/basic-components
Project-URL: Documentation, https://components.basicmachines.co
Project-URL: Repository, https://github.com/basicmachines-co/basic-components
Project-URL: Changelog, https://github.com/basicmachines-co/basic-components/blob/main/CHANGELOG.md
Project-URL: Issues, https://github.com/basicmachines-co/basic-components/issues
Author-email: phernandez <paul@basicmachines.co>
License: MIT
Keywords: alpinejs,components,django,fastapi,flask,frontend,htmx,jinja,jinjax,server-side,shadcn,shadcnui,tailwind,ui,web
Classifier: Development Status :: 4 - Beta
Classifier: Environment :: Web Environment
Classifier: Framework :: Django
Classifier: Framework :: FastAPI
Classifier: Framework :: Flask
Classifier: Intended Audience :: Developers
Classifier: License :: OSI Approved :: MIT License
Classifier: Operating System :: OS Independent
Classifier: Programming Language :: Python :: 3
Classifier: Programming Language :: Python :: 3.10
Classifier: Programming Language :: Python :: 3.11
Classifier: Programming Language :: Python :: 3.12
Classifier: Topic :: Internet :: WWW/HTTP
Classifier: Topic :: Software Development :: Libraries :: Python Modules
Classifier: Topic :: Software Development :: User Interfaces
Classifier: Typing :: Typed
Requires-Python: >=3.10
Requires-Dist: copier>=9.4.1
Requires-Dist: rich>=13.7.0
Requires-Dist: tomli-w>=1.1.0
Requires-Dist: tomli>=2.0.2
Requires-Dist: typer>=0.9.0
Provides-Extra: dev
Requires-Dist: black>=24.1.0; extra == 'dev'
Requires-Dist: isort>=5.13.0; extra == 'dev'
Requires-Dist: mypy>=1.8.0; extra == 'dev'
Requires-Dist: python-semantic-release>=9.14.0; extra == 'dev'
Requires-Dist: ruff>=0.2.0; extra == 'dev'
Provides-Extra: docs
Requires-Dist: arel>=0.3.0; extra == 'docs'
Requires-Dist: copier>=9.4.1; extra == 'docs'
Requires-Dist: fastapi[standard]>=0.115.4; extra == 'docs'
Requires-Dist: icecream>=2.1.3; extra == 'docs'
Requires-Dist: jinja2>=3.1.3; extra == 'docs'
Requires-Dist: jinjax[whitenoise]>=0.47; extra == 'docs'
Requires-Dist: loguru>=0.7.2; extra == 'docs'
Requires-Dist: markdown>=3.7; extra == 'docs'
Requires-Dist: markupsafe>=3.0.2; extra == 'docs'
Requires-Dist: pydantic-settings>=2.6.0; extra == 'docs'
Requires-Dist: pydantic>=2.9.2; extra == 'docs'
Requires-Dist: pygments>=2.17.2; extra == 'docs'
Requires-Dist: pymdown-extensions>=10.12; extra == 'docs'
Requires-Dist: pyright>=1.1.385; extra == 'docs'
Requires-Dist: pytest-playwright>=0.5.2; extra == 'docs'
Requires-Dist: pytest>=8.3.3; extra == 'docs'
Requires-Dist: python-frontmatter>=1.1.0; extra == 'docs'
Requires-Dist: setuptools>=75.5.0; extra == 'docs'
Requires-Dist: starlette-wtf>=0.4.5; extra == 'docs'
Requires-Dist: uvicorn>=0.32.0; extra == 'docs'
Requires-Dist: watchfiles>=0.24.0; extra == 'docs'
Requires-Dist: websockets>=13.1; extra == 'docs'
Requires-Dist: wtforms>=3.2.1; extra == 'docs'
Provides-Extra: full
Requires-Dist: arel>=0.3.0; extra == 'full'
Requires-Dist: black>=24.1.0; extra == 'full'
Requires-Dist: copier>=9.4.1; extra == 'full'
Requires-Dist: fastapi[standard]>=0.115.4; extra == 'full'
Requires-Dist: icecream>=2.1.3; extra == 'full'
Requires-Dist: isort>=5.13.0; extra == 'full'
Requires-Dist: jinja2>=3.1.3; extra == 'full'
Requires-Dist: jinjax>=0.47; extra == 'full'
Requires-Dist: jinjax[whitenoise]>=0.47; extra == 'full'
Requires-Dist: loguru>=0.7.2; extra == 'full'
Requires-Dist: markdown>=3.7; extra == 'full'
Requires-Dist: markupsafe>=3.0.2; extra == 'full'
Requires-Dist: mypy>=1.8.0; extra == 'full'
Requires-Dist: pydantic-settings>=2.6.0; extra == 'full'
Requires-Dist: pydantic>=2.9.2; extra == 'full'
Requires-Dist: pygments>=2.17.2; extra == 'full'
Requires-Dist: pymdown-extensions>=10.12; extra == 'full'
Requires-Dist: pyright>=1.1.385; extra == 'full'
Requires-Dist: pytest-playwright>=0.5.2; extra == 'full'
Requires-Dist: pytest>=8.3.3; extra == 'full'
Requires-Dist: python-frontmatter>=1.1.0; extra == 'full'
Requires-Dist: python-semantic-release>=9.14.0; extra == 'full'
Requires-Dist: ruff>=0.2.0; extra == 'full'
Requires-Dist: setuptools>=75.5.0; extra == 'full'
Requires-Dist: starlette-wtf>=0.4.5; extra == 'full'
Requires-Dist: uvicorn>=0.32.0; extra == 'full'
Requires-Dist: watchfiles>=0.24.0; extra == 'full'
Requires-Dist: websockets>=13.1; extra == 'full'
Requires-Dist: wtforms>=3.2.1; extra == 'full'
Provides-Extra: utils
Requires-Dist: jinja2>=3.1.3; extra == 'utils'
Requires-Dist: jinjax>=0.47; extra == 'utils'
